{
  "assets": {
    "EUR/USD": {
      "activo": "EUR/USD",
      "advertencias": [
        "No hay patrón confirmado en la última vela analizada.",
        "EMA 50 y EMA 200 están muy juntas y sin dirección clara.",
        "Sin patrón confirmado, no se habilita una posible operación."
      ],
      "alineacion": "Confirmada",
      "contexto_1h": "BAJISTA",
      "contexto_4h": "BAJISTA",
      "entrada": "NO HABILITADA",
      "motivos": [
        "El precio está por debajo de EMA 50/200 o reaccionando bajo ellas.",
        "Posible ruptura bajista de rango, pero falta cierre de confirmación."
      ],
      "precio": 1.1384334564208984,
      "precio_texto": "1.13843",
      "score": 45,
      "semaforo": "VIGILAR",
      "sesgo": "VENTA",
      "symbol": "EURUSD=X",
      "temporalidad": "1H",
      "tendencia": "Lateral",
      "timestamp": "2026-07-17T00:00:00"
    },
    "Oro": {
      "activo": "Oro",
      "advertencias": [
        "La senal local y el sesgo multi-temporal no coinciden; evitar operar contra el contexto permitido.",
        "No hay patrón confirmado en la última vela analizada.",
        "La tendencia actual va en contra del sesgo operativo.",
        "Sin patrón confirmado, no se habilita una posible operación."
      ],
      "alineacion": "Confirmada",
      "contexto_1h": "BAJISTA",
      "contexto_4h": "BAJISTA",
      "entrada": "NO HABILITADA",
      "motivos": [
        "4H bajista + 1H bajista = alineacion confirmada.",
        "El sesgo permitido es venta, pero la lectura actual de 1H no coincide con ese sesgo.",
        "Hasta que la senal de entrada vuelva a alinearse con la multi-temporalidad, la entrada permanece en espera."
      ],
      "precio": 4008.300048828125,
      "precio_texto": "4008.30",
      "score": 45,
      "semaforo": "VIGILAR",
      "sesgo": "VENTA",
      "symbol": "GC=F",
      "temporalidad": "1H",
      "tendencia": "Bajista",
      "timestamp": "2026-07-17T00:00:00"
    },
    "Petróleo WTI": {
      "activo": "Petróleo WTI",
      "advertencias": [
        "La senal local y el sesgo multi-temporal no coinciden; evitar operar contra el contexto permitido.",
        "No hay patrón confirmado en la última vela analizada.",
        "La tendencia actual va en contra del sesgo operativo.",
        "Sin patrón confirmado, no se habilita una posible operación."
      ],
      "alineacion": "Confirmada",
      "contexto_1h": "ALCISTA",
      "contexto_4h": "ALCISTA",
      "entrada": "NO HABILITADA",
      "motivos": [
        "4H alcista con tendencia lateral + 1H alcista = no hay alineacion completa; esperar confirmacion.",
        "El sesgo permitido es compra, pero la lectura actual de 1H no coincide con ese sesgo.",
        "Hasta que la senal de entrada vuelva a alinearse con la multi-temporalidad, la entrada permanece en espera."
      ],
      "precio": 77.93000030517578,
      "precio_texto": "77.93",
      "score": 45,
      "semaforo": "VIGILAR",
      "sesgo": "COMPRA",
      "symbol": "CL=F",
      "temporalidad": "1H",
      "tendencia": "Alcista",
      "timestamp": "2026-07-17T00:00:00"
    }
  },
  "checked_at": "2026-07-13T21:08:59.983515+00:00"
}
